metrosp/__init__.py
metrosp/metrosp.py
metrosp-1.0.2.dist-info/METADATA
metrosp-1.0.2.dist-info/WHEEL
metrosp-1.0.2.dist-info/top_level.txt
metrosp-1.0.2.dist-info/RECORD
