Metadata-Version: 2.1
Name: metrosp
Version: 1.0.2
Summary: Ferramenta de linha de comando para recuperar situação atual do Metro de SP
Home-page: https://github.com/renatolipi/status_metro_sp
Author: Renato Lipi
Author-email: 
License: LGPLv3
Keywords: metro metrosp SP
Classifier: Programming Language :: Python :: 3.10
Requires-Dist: beautifulsoup4==4.12.3
Requires-Dist: requests==2.32.3
